miditk/__init__.py
miditk/common/__init__.py
miditk/common/constants.py
miditk/smf/__init__.py
miditk/smf/api.py
miditk/smf/converters.py
miditk/smf/parser.py
miditk/smf/reader.py
miditk/smf/sequence.py
miditk/smf/version.py
miditk/smf/writer.py
miditk/smf/scripts/__init__.py
miditk/smf/scripts/mid2syx.py
miditk_smf-0.3.1.dist-info/METADATA
miditk_smf-0.3.1.dist-info/WHEEL
miditk_smf-0.3.1.dist-info/entry_points.txt
miditk_smf-0.3.1.dist-info/licenses/LICENSE.md
miditk_smf-0.3.1.dist-info/RECORD
